<?xml version="1.0" encoding="UTF-8"?>
<objects serializationModel="Studio.02.01.00">
	<object class="AudioFile" id="{32faf4e1-ed32-4da5-8d8d-6c5d616edd77}">
		<property name="assetPath">
			<value>SFX/Vol_2 Sound Pack_6.wav</value>
		</property>
		<property name="frequencyInKHz">
			<value>44.0999985</value>
		</property>
		<property name="channelCount">
			<value>2</value>
		</property>
		<property name="length">
			<value>0.46342403628117912</value>
		</property>
		<relationship name="masterAssetFolder">
			<destination>{f4e6d99c-285d-4c95-9776-b9123c3884ae}</destination>
		</relationship>
	</object>
</objects>
